odoo/addons/product_brand_purchase_report/README.rst
odoo/addons/product_brand_purchase_report/__init__.py
odoo/addons/product_brand_purchase_report/__manifest__.py
odoo/addons/product_brand_purchase_report/i18n/product_brand_purchase_report.pot
odoo/addons/product_brand_purchase_report/readme/CONTRIBUTORS.rst
odoo/addons/product_brand_purchase_report/readme/DESCRIPTION.rst
odoo/addons/product_brand_purchase_report/readme/USAGE.rst
odoo/addons/product_brand_purchase_report/reports/__init__.py
odoo/addons/product_brand_purchase_report/reports/purchase_report.py
odoo/addons/product_brand_purchase_report/reports/purchase_report_view.xml
odoo/addons/product_brand_purchase_report/static/description/icon.png
odoo/addons/product_brand_purchase_report/static/description/index.html
odoo13_addon_product_brand_purchase_report-13.0.1.0.1.dev3.dist-info/METADATA
odoo13_addon_product_brand_purchase_report-13.0.1.0.1.dev3.dist-info/WHEEL
odoo13_addon_product_brand_purchase_report-13.0.1.0.1.dev3.dist-info/top_level.txt
odoo13_addon_product_brand_purchase_report-13.0.1.0.1.dev3.dist-info/RECORD
